t3co/__init__.py
t3co/sweep.py
t3co/demos/Spencer.py
t3co/demos/example_load_and_run.py
t3co/demos/hev_sweep_and_moo.py
t3co/demos/opp_cost_demo.py
t3co/demos/t2co_opt_benchmark.py
t3co/demos/visualization_demo.py
t3co/demos/notebooks/2022-07-24_raw_t3co-withmidandlow-andadjmsrp.csv
t3co/demos/notebooks/all_bench.csv
t3co/demos/notebooks/diesel_bench.csv
t3co/demos/prototyping_and_troubleshooting/plf_testing_no_min_ltwt/ensemble_run_no_ltwt_mins_strict_tols_results_2023-03-29_20-04-05.csv
t3co/moopack/__init__.py
t3co/moopack/moo.py
t3co/objectives/__init__.py
t3co/objectives/accel.py
t3co/objectives/fueleconomy.py
t3co/objectives/gradeability.py
t3co/resources/T3COConfig.csv
t3co/resources/auxiliary/AeroDragImprovementCostCurve.csv
t3co/resources/auxiliary/BaselineVehicle.csv
t3co/resources/auxiliary/EngineEffImprovementCostCurve.csv
t3co/resources/auxiliary/FASTSimInputsHeader.csv
t3co/resources/auxiliary/FASTSimOutputs.csv
t3co/resources/auxiliary/FASTSimOutputsHeader.csv
t3co/resources/auxiliary/FuelPrices.csv
t3co/resources/auxiliary/LightweightImprovementCostCurve.csv
t3co/resources/auxiliary/OptimizerInitializationValues.csv
t3co/resources/auxiliary/OtherInputsHeader.csv
t3co/resources/auxiliary/PowertrainTechTargets.csv
t3co/resources/auxiliary/ResidualValues.csv
t3co/resources/auxiliary/VocationRequirements.csv
t3co/resources/auxiliary/daily_distance_pdf.csv
t3co/resources/auxiliary/tractorweightvars.csv
t3co/resources/benchmarkdata/t2co_secnarios_file.csv
t3co/resources/benchmarkdata/t2cobenchmarkFASTSimInputs.csv
t3co/resources/benchmarkdata/t3cobenchmarkFASTSimInputs.csv
t3co/resources/benchmarkdata/t3cobenchmarkOtherInputs.csv
t3co/resources/cycles/C8_LineHaul_Lammert.csv
t3co/resources/cycles/EPA_Ph2_rural_interstate_65mph.csv
t3co/resources/cycles/EPA_Ph2_transient.csv
t3co/resources/cycles/EPA_Ph2_urban_highway_55mph.csv
t3co/resources/cycles/RefuseDriveCycle.csv
t3co/resources/cycles/accel.csv
t3co/resources/cycles/long_haul_cyc.csv
t3co-1.0.11.dist-info/METADATA
t3co-1.0.11.dist-info/WHEEL
t3co-1.0.11.dist-info/entry_points.txt
t3co-1.0.11.dist-info/licenses/LICENSE
t3co-1.0.11.dist-info/RECORD
