Metadata-Version: 2.4
Name: t3co
Version: 1.0.11
Summary: NREL's Transportation Technology Total Cost of Ownership tool
Project-URL: Homepage, https://www.nrel.gov/transportation/t3co.html
Project-URL: Documentation, https://nrel.github.io/T3CO
Project-URL: Repository, https://github.com/NREL/T3CO
Project-URL: Bug Tracker, https://github.com/NREL/T3CO/issues
Author-email: Harish Panneer Selvam <Harish.PanneerSelvam@nrel.gov>, Alicia Birky <Alicia.Birky@nrel.gov>, Chad Baker <Chad.Baker@nrel.gov>
Maintainer-email: NREL-AVCI <t3co@nrel.gov>
License: BSD 3-Clause License
License-File: LICENSE
Keywords: tco,total-cost,total-cost-of-ownership,vehicle-cost,vehicle-simulation
Classifier: Development Status :: 3 - Alpha
Classifier: Intended Audience :: Developers
Classifier: Intended Audience :: Education
Classifier: Intended Audience :: Science/Research
Classifier: License :: OSI Approved :: BSD License
Classifier: Programming Language :: Python :: 3 :: Only
Classifier: Programming Language :: Python :: 3.8
Classifier: Programming Language :: Python :: 3.9
Classifier: Programming Language :: Python :: 3.10
Classifier: Topic :: Scientific/Engineering
Requires-Python: >=3.8
Requires-Dist: fastsim==2.1.1
Requires-Dist: numpy==1.24.1
Requires-Dist: pandas==2.0.3
Requires-Dist: pymoo==0.6.1
Requires-Dist: scipy==1.10.1
